verilog_src/AGU.v
module AGU #(
    parameter N = 32,
    stage_width = $clog2($clog2(N)),
    pair_id_width = $clog2(N/2),
    address_width = $clog2(N)
) (
    input wire clk, reset,
    input wire [stage_width-1: 0] stage,
    input wire [pair_id_width - 1: 0] pair_id, 
    output reg [address_width -1 : 0] address1, address2, 
    output reg [address_width -1: 0] twiddle_address
);


// N is the number of samples in the fourier transform
// log2N is the number of bits neccessary to represent N different states
// since the FFT has log2(N) stages, we need log2N bits to encode the stages
// we operate on pairs of samples => we need log(N/2) == logN2 -1 bits to encode pairs
localparam log2N = $clog2(N);
 
// signal declaration
//reg [log2N-1: 0] stage_reg;
//reg [(log2N -1)- 1: 0] pair_id_reg;
reg [address_width -1: 0] i_address1, i_address2;  

// addresses for the samples in the pair are computed as
// ROT_N_(2*pair_id, stage), ROT_N_(2*pair_id+1, stage)

// Twiddle address is computed by masking the LS log2N-stage-1 bits of pair_id

reg [pair_id_width : 0] pair_id_x_2, pair_id_x_2_1; // (pair_id*2, pair_id*2+1)
reg [address_width-1: 0] i_twiddle_address;
reg [address_width: 0] mask;
reg [address_width: 0] mask_;
// integer i; 

always @(*)begin
    pair_id_x_2 = {pair_id, 1'b0}; 

    //OR can be used to add 1 since the last bit of pair_id_x_2 is necessarily 0
    pair_id_x_2_1 = {pair_id, 1'b1};
    i_address1 = barrel_shift_left(pair_id_x_2, stage);
    i_address2 = barrel_shift_left(pair_id_x_2_1, stage);
    mask = (1'b1 << stage);
    mask_ = mask - 1'b1;
    i_twiddle_address = mask_[log2N-1:0] & pair_id; 
    
    //generate 
    // for (i = 0; i<log2N-1; i = i + 1) begin
    //     if (i < log2N-stage-1) 
    //         twiddle_address_reg[i] = pair_id[i]; 
    //     else
    //         twiddle_address_reg[i] = 1'b0; 
    // end
    //endgenerate

end

always @(posedge clk, posedge reset) begin
    // pair_id_reg <= pair_id; 
    // stage_reg <= stage;

    if (reset) begin
        address1 <= 0; 
        address2 <= 0; 
        twiddle_address <= 0; 
    end else begin
        address1 <= i_address1;
        address2 <= i_address2;
        twiddle_address <= i_twiddle_address;
    end
end


// barrel shift vector j by vector i
function [log2N-1:0] barrel_shift_left;
    input [pair_id_width: 0] j; //vector to be barrel shifted
    input [stage_width-1: 0] i; // amount to shift by

    reg [stage_width-1: 0] max_index, temp;
    reg [2*pair_id_width+1: 0] doublej;

    //reg  [log2N-1:0] temp;
    begin
        max_index = log2N & {stage_width{1'b1}};
        doublej = {j, j};
        temp = max_index - i; 
        barrel_shift_left = doublej[temp+:log2N];   
    end 
    
    
endfunction
    
endmodule

verilog_src/v_test_benches/AGU_tb.v
// AGU Testbench

module AGU_tb;

// Parameters
localparam  N = 32;
localparam stage_id_width = $clog2($clog2(N));
localparam pair_id_width = $clog2(N/2);
localparam address_width = $clog2(N);


// Ports
reg  clk = 0;
reg reset; 
reg [stage_id_width-1: 0] stage_id;
reg [pair_id_width - 1: 0] pair_id;
wire [address_width -1 : 0] address1, address2;
wire [address_width -1: 0] twiddle_address;

AGU #(.N ( N )) AGU_dut (
  .clk (clk ),
  .reset(reset),
  .stage (stage_id ),
  .pair_id (pair_id ),
  .address1 (address1 ),
  .address2 (address2 ),
  .twiddle_address (twiddle_address)
);


initial begin
    $dumpfile("AGU.vcd");
    $dumpvars(0, AGU_tb);
end

initial begin
  begin 
    stage_id <= {stage_id_width{1'b0}};
    pair_id <= {pair_id_width{1'b0}};
    //$finish;
  end
end

initial begin 
  reset = 1'b1;
  #(10);
  reset = 1'b0; 
end

always @(posedge clk) begin
    pair_id <= pair_id + 1'b1;
    if (pair_id == 15)begin
      if ((stage_id == 4))
        $finish;
      else stage_id <= stage_id + 1'b1; 
    end
end

always
  #20  clk = ! clk ;

endmodule

verilog_src/vcd_traces/AGU.vcd
$date
	Thu Aug 25 22:54:18 2022
$end
$version
	Icarus Verilog
$end
$timescale
	1s
$end
$scope module AGU_tb $end
$var wire 5 ! twiddle_address [4:0] $end
$var wire 5 " address2 [4:0] $end
$var wire 5 # address1 [4:0] $end
$var parameter 32 $ N $end
$var parameter 32 % address_width $end
$var parameter 32 & pair_id_width $end
$var parameter 32 ' stage_id_width $end
$var reg 1 ( clk $end
$var reg 4 ) pair_id [3:0] $end
$var reg 1 * reset $end
$var reg 3 + stage_id [2:0] $end
$scope module AGU_dut $end
$var wire 1 ( clk $end
$var wire 4 , pair_id [3:0] $end
$var wire 1 * reset $end
$var wire 3 - stage [2:0] $end
$var parameter 32 . N $end
$var parameter 32 / address_width $end
$var parameter 32 0 log2N $end
$var parameter 32 1 pair_id_width $end
$var parameter 32 2 stage_width $end
$var reg 5 3 address1 [4:0] $end
$var reg 5 4 address2 [4:0] $end
$var reg 5 5 i_address1 [4:0] $end
$var reg 5 6 i_address2 [4:0] $end
$var reg 5 7 i_twiddle_address [4:0] $end
$var reg 6 8 mask [5:0] $end
$var reg 6 9 mask_ [5:0] $end
$var reg 5 : pair_id_x_2 [4:0] $end
$var reg 5 ; pair_id_x_2_1 [4:0] $end
$var reg 5 < twiddle_address [4:0] $end
$scope function barrel_shift_left $end
$var reg 10 = doublej [9:0] $end
$var reg 3 > i [2:0] $end
$var reg 5 ? j [4:0] $end
$var reg 3 @ max_index [2:0] $end
$var reg 3 A temp [2:0] $end
$upscope $end
$upscope $end
$upscope $end
$enddefinitions $end
$comment Show the parameter values. $end
$dumpall
b11 2
b100 1
b101 0
b101 /
b100000 .
b11 '
b100 &
b101 %
b100000 $
$end
#0
$dumpvars
b101 A
b101 @
b1 ?
b0 >
b100001 =
b0 <
b1 ;
b0 :
b0 9
b1 8
b0 7
b1 6
b0 5
b0 4
b0 3
b0 -
b0 ,
b0 +
1*
b0 )
0(
b0 #
b0 "
b0 !
$end
#10
0*
#20
b11 6
b10 5
b1100011 =
b11 ?
b11 ;
b10 :
b1 "
b1 4
b1 )
b1 ,
1(
#40
0(
#60
b101 6
b100 5
b10100101 =
b101 ?
b101 ;
b100 :
b11 "
b11 4
b10 #
b10 3
b10 )
b10 ,
1(
#80
0(
#100
b111 6
b110 5
b11100111 =
b111 ?
b111 ;
b110 :
b101 "
b101 4
b100 #
b100 3
b11 )
b11 ,
1(
#120
0(
#140
b1001 6
b1000 5
b100101001 =
b1001 ?
b1001 ;
b1000 :
b111 "
b111 4
b110 #
b110 3
b100 )
b100 ,
1(
#160
0(
#180
b1011 6
b1010 5
b101101011 =
b1011 ?
b1011 ;
b1010 :
b1001 "
b1001 4
b1000 #
b1000 3
b101 )
b101 ,
1(
#200
0(
#220
b1101 6
b1100 5
b110101101 =
b1101 ?
b1101 ;
b1100 :
b1011 "
b1011 4
b1010 #
b1010 3
b110 )
b110 ,
1(
#240
0(
#260
b1111 6
b1110 5
b111101111 =
b1111 ?
b1111 ;
b1110 :
b1101 "
b1101 4
b1100 #
b1100 3
b111 )
b111 ,
1(
#280
0(
#300
b10001 6
b10000 5
b1000110001 =
b10001 ?
b10001 ;
b10000 :
b1111 "
b1111 4
b1110 #
b1110 3
b1000 )
b1000 ,
1(
#320
0(
#340
b10011 6
b10010 5
b1001110011 =
b10011 ?
b10011 ;
b10010 :
b10001 "
b10001 4
b10000 #
b10000 3
b1001 )
b1001 ,
1(
#360
0(
#380
b10101 6
b10100 5
b1010110101 =
b10101 ?
b10101 ;
b10100 :
b10011 "
b10011 4
b10010 #
b10010 3
b1010 )
b1010 ,
1(
#400
0(
#420
b10111 6
b10110 5
b1011110111 =
b10111 ?
b10111 ;
b10110 :
b10101 "
b10101 4
b10100 #
b10100 3
b1011 )
b1011 ,
1(
#440
0(
#460
b11001 6
b11000 5
b1100111001 =
b11001 ?
b11001 ;
b11000 :
b10111 "
b10111 4
b10110 #
b10110 3
b1100 )
b1100 ,
1(
#480
0(
#500
b11011 6
b11010 5
b1101111011 =
b11011 ?
b11011 ;
b11010 :
b11001 "
b11001 4
b11000 #
b11000 3
b1101 )
b1101 ,
1(
#520
0(
#540
b11101 6
b11100 5
b1110111101 =
b11101 ?
b11101 ;
b11100 :
b11011 "
b11011 4
b11010 #
b11010 3
b1110 )
b1110 ,
1(
#560
0(
#580
b11111 6
b11110 5
b1111111111 =
b11111 ?
b11111 ;
b11110 :
b11101 "
b11101 4
b11100 #
b11100 3
b1111 )
b1111 ,
1(
#600
0(
#620
b1 9
b10 8
b10 6
b0 5
b100 A
b100001 =
b1 ?
b1 >
b1 ;
b0 :
b11111 "
b11111 4
b11110 #
b11110 3
b1 +
b1 -
b0 )
b0 ,
1(
#640
0(
#660
b1 7
b110 6
b100 5
b1100011 =
b11 ?
b11 ;
b10 :
b10 "
b10 4
b0 #
b0 3
b1 )
b1 ,
1(
#680
0(
#700
b0 7
b1010 6
b1000 5
b10100101 =
b101 ?
b101 ;
b100 :
b1 !
b1 <
b110 "
b110 4
b100 #
b100 3
b10 )
b10 ,
1(
#720
0(
#740
b1 7
b1110 6
b1100 5
b11100111 =
b111 ?
b111 ;
b110 :
b0 !
b0 <
b1010 "
b1010 4
b1000 #
b1000 3
b11 )
b11 ,
1(
#760
0(
#780
b0 7
b10010 6
b10000 5
b100101001 =
b1001 ?
b1001 ;
b1000 :
b1 !
b1 <
b1110 "
b1110 4
b1100 #
b1100 3
b100 )
b100 ,
1(
#800
0(
#820
b1 7
b10110 6
b10100 5
b101101011 =
b1011 ?
b1011 ;
b1010 :
b0 !
b0 <
b10010 "
b10010 4
b10000 #
b10000 3
b101 )
b101 ,
1(
#840
0(
#860
b0 7
b11010 6
b11000 5
b110101101 =
b1101 ?
b1101 ;
b1100 :
b1 !
b1 <
b10110 "
b10110 4
b10100 #
b10100 3
b110 )
b110 ,
1(
#880
0(
#900
b1 7
b11110 6
b11100 5
b111101111 =
b1111 ?
b1111 ;
b1110 :
b0 !
b0 <
b11010 "
b11010 4
b11000 #
b11000 3
b111 )
b111 ,
1(
#920
0(
#940
b0 7
b11 6
b1 5
b1000110001 =
b10001 ?
b10001 ;
b10000 :
b1 !
b1 <
b11110 "
b11110 4
b11100 #
b11100 3
b1000 )
b1000 ,
1(
#960
0(
#980
b1 7
b111 6
b101 5
b1001110011 =
b10011 ?
b10011 ;
b10010 :
b0 !
b0 <
b11 "
b11 4
b1 #
b1 3
b1001 )
b1001 ,
1(
#1000
0(
#1020
b0 7
b1011 6
b1001 5
b1010110101 =
b10101 ?
b10101 ;
b10100 :
b1 !
b1 <
b111 "
b111 4
b101 #
b101 3
b1010 )
b1010 ,
1(
#1040
0(
#1060
b1 7
b1111 6
b1101 5
b1011110111 =
b10111 ?
b10111 ;
b10110 :
b0 !
b0 <
b1011 "
b1011 4
b1001 #
b1001 3
b1011 )
b1011 ,
1(
#1080
0(
#1100
b0 7
b10011 6
b10001 5
b1100111001 =
b11001 ?
b11001 ;
b11000 :
b1 !
b1 <
b1111 "
b1111 4
b1101 #
b1101 3
b1100 )
b1100 ,
1(
#1120
0(
#1140
b1 7
b10111 6
b10101 5
b1101111011 =
b11011 ?
b11011 ;
b11010 :
b0 !
b0 <
b10011 "
b10011 4
b10001 #
b10001 3
b1101 )
b1101 ,
1(
#1160
0(
#1180
b0 7
b11011 6
b11001 5
b1110111101 =
b11101 ?
b11101 ;
b11100 :
b1 !
b1 <
b10111 "
b10111 4
b10101 #
b10101 3
b1110 )
b1110 ,
1(
#1200
0(
#1220
b1 7
b11111 6
b11101 5
b1111111111 =
b11111 ?
b11111 ;
b11110 :
b0 !
b0 <
b11011 "
b11011 4
b11001 #
b11001 3
b1111 )
b1111 ,
1(
#1240
0(
#1260
b0 7
b11 9
b100 8
b100 6
b0 5
b11 A
b100001 =
b1 ?
b10 >
b1 ;
b0 :
b1 !
b1 <
b11111 "
b11111 4
b11101 #
b11101 3
b10 +
b10 -
b0 )
b0 ,
1(
#1280
0(
#1300
b1 7
b1100 6
b1000 5
b1100011 =
b11 ?
b11 ;
b10 :
b0 !
b0 <
b100 "
b100 4
b0 #
b0 3
b1 )
b1 ,
1(
#1320
0(
#1340
b10 7
b10100 6
b10000 5
b10100101 =
b101 ?
b101 ;
b100 :
b1 !
b1 <
b1100 "
b1100 4
b1000 #
b1000 3
b10 )
b10 ,
1(
#1360
0(
#1380
b11 7
b11100 6
b11000 5
b11100111 =
b111 ?
b111 ;
b110 :
b10 !
b10 <
b10100 "
b10100 4
b10000 #
b10000 3
b11 )
b11 ,
1(
#1400
0(
#1420
b0 7
b101 6
b1 5
b100101001 =
b1001 ?
b1001 ;
b1000 :
b11 !
b11 <
b11100 "
b11100 4
b11000 #
b11000 3
b100 )
b100 ,
1(
#1440
0(
#1460
b1 7
b1101 6
b1001 5
b101101011 =
b1011 ?
b1011 ;
b1010 :
b0 !
b0 <
b101 "
b101 4
b1 #
b1 3
b101 )
b101 ,
1(
#1480
0(
#1500
b10 7
b10101 6
b10001 5
b110101101 =
b1101 ?
b1101 ;
b1100 :
b1 !
b1 <
b1101 "
b1101 4
b1001 #
b1001 3
b110 )
b110 ,
1(
#1520
0(
#1540
b11 7
b11101 6
b11001 5
b111101111 =
b1111 ?
b1111 ;
b1110 :
b10 !
b10 <
b10101 "
b10101 4
b10001 #
b10001 3
b111 )
b111 ,
1(
#1560
0(
#1580
b0 7
b110 6
b10 5
b1000110001 =
b10001 ?
b10001 ;
b10000 :
b11 !
b11 <
b11101 "
b11101 4
b11001 #
b11001 3
b1000 )
b1000 ,
1(
#1600
0(
#1620
b1 7
b1110 6
b1010 5
b1001110011 =
b10011 ?
b10011 ;
b10010 :
b0 !
b0 <
b110 "
b110 4
b10 #
b10 3
b1001 )
b1001 ,
1(
#1640
0(
#1660
b10 7
b10110 6
b10010 5
b1010110101 =
b10101 ?
b10101 ;
b10100 :
b1 !
b1 <
b1110 "
b1110 4
b1010 #
b1010 3
b1010 )
b1010 ,
1(
#1680
0(
#1700
b11 7
b11110 6
b11010 5
b1011110111 =
b10111 ?
b10111 ;
b10110 :
b10 !
b10 <
b10110 "
b10110 4
b10010 #
b10010 3
b1011 )
b1011 ,
1(
#1720
0(
#1740
b0 7
b111 6
b11 5
b1100111001 =
b11001 ?
b11001 ;
b11000 :
b11 !
b11 <
b11110 "
b11110 4
b11010 #
b11010 3
b1100 )
b1100 ,
1(
#1760
0(
#1780
b1 7
b1111 6
b1011 5
b1101111011 =
b11011 ?
b11011 ;
b11010 :
b0 !
b0 <
b111 "
b111 4
b11 #
b11 3
b1101 )
b1101 ,
1(
#1800
0(
#1820
b10 7
b10111 6
b10011 5
b1110111101 =
b11101 ?
b11101 ;
b11100 :
b1 !
b1 <
b1111 "
b1111 4
b1011 #
b1011 3
b1110 )
b1110 ,
1(
#1840
0(
#1860
b11 7
b11111 6
b11011 5
b1111111111 =
b11111 ?
b11111 ;
b11110 :
b10 !
b10 <
b10111 "
b10111 4
b10011 #
b10011 3
b1111 )
b1111 ,
1(
#1880
0(
#1900
b0 7
b111 9
b1000 8
b1000 6
b0 5
b10 A
b100001 =
b1 ?
b11 >
b1 ;
b0 :
b11 !
b11 <
b11111 "
b11111 4
b11011 #
b11011 3
b11 +
b11 -
b0 )
b0 ,
1(
#1920
0(
#1940
b1 7
b11000 6
b10000 5
b1100011 =
b11 ?
b11 ;
b10 :
b0 !
b0 <
b1000 "
b1000 4
b0 #
b0 3
b1 )
b1 ,
1(
#1960
0(
#1980
b10 7
b1001 6
b1 5
b10100101 =
b101 ?
b101 ;
b100 :
b1 !
b1 <
b11000 "
b11000 4
b10000 #
b10000 3
b10 )
b10 ,
1(
#2000
0(
#2020
b11 7
b11001 6
b10001 5
b11100111 =
b111 ?
b111 ;
b110 :
b10 !
b10 <
b1001 "
b1001 4
b1 #
b1 3
b11 )
b11 ,
1(
#2040
0(
#2060
b100 7
b1010 6
b10 5
b100101001 =
b1001 ?
b1001 ;
b1000 :
b11 !
b11 <
b11001 "
b11001 4
b10001 #
b10001 3
b100 )
b100 ,
1(
#2080
0(
#2100
b101 7
b11010 6
b10010 5
b101101011 =
b1011 ?
b1011 ;
b1010 :
b100 !
b100 <
b1010 "
b1010 4
b10 #
b10 3
b101 )
b101 ,
1(
#2120
0(
#2140
b110 7
b1011 6
b11 5
b110101101 =
b1101 ?
b1101 ;
b1100 :
b101 !
b101 <
b11010 "
b11010 4
b10010 #
b10010 3
b110 )
b110 ,
1(
#2160
0(
#2180
b111 7
b11011 6
b10011 5
b111101111 =
b1111 ?
b1111 ;
b1110 :
b110 !
b110 <
b1011 "
b1011 4
b11 #
b11 3
b111 )
b111 ,
1(
#2200
0(
#2220
b0 7
b1100 6
b100 5
b1000110001 =
b10001 ?
b10001 ;
b10000 :
b111 !
b111 <
b11011 "
b11011 4
b10011 #
b10011 3
b1000 )
b1000 ,
1(
#2240
0(
#2260
b1 7
b11100 6
b10100 5
b1001110011 =
b10011 ?
b10011 ;
b10010 :
b0 !
b0 <
b1100 "
b1100 4
b100 #
b100 3
b1001 )
b1001 ,
1(
#2280
0(
#2300
b10 7
b1101 6
b101 5
b1010110101 =
b10101 ?
b10101 ;
b10100 :
b1 !
b1 <
b11100 "
b11100 4
b10100 #
b10100 3
b1010 )
b1010 ,
1(
#2320
0(
#2340
b11 7
b11101 6
b10101 5
b1011110111 =
b10111 ?
b10111 ;
b10110 :
b10 !
b10 <
b1101 "
b1101 4
b101 #
b101 3
b1011 )
b1011 ,
1(
#2360
0(
#2380
b100 7
b1110 6
b110 5
b1100111001 =
b11001 ?
b11001 ;
b11000 :
b11 !
b11 <
b11101 "
b11101 4
b10101 #
b10101 3
b1100 )
b1100 ,
1(
#2400
0(
#2420
b101 7
b11110 6
b10110 5
b1101111011 =
b11011 ?
b11011 ;
b11010 :
b100 !
b100 <
b1110 "
b1110 4
b110 #
b110 3
b1101 )
b1101 ,
1(
#2440
0(
#2460
b110 7
b1111 6
b111 5
b1110111101 =
b11101 ?
b11101 ;
b11100 :
b101 !
b101 <
b11110 "
b11110 4
b10110 #
b10110 3
b1110 )
b1110 ,
1(
#2480
0(
#2500
b111 7
b11111 6
b10111 5
b1111111111 =
b11111 ?
b11111 ;
b11110 :
b110 !
b110 <
b1111 "
b1111 4
b111 #
b111 3
b1111 )
b1111 ,
1(
#2520
0(
#2540
b0 7
b1111 9
b10000 8
b10000 6
b0 5
b1 A
b100001 =
b1 ?
b100 >
b1 ;
b0 :
b111 !
b111 <
b11111 "
b11111 4
b10111 #
b10111 3
b100 +
b100 -
b0 )
b0 ,
1(
#2560
0(
#2580
b1 7
b10001 6
b1 5
b1100011 =
b11 ?
b11 ;
b10 :
b0 !
b0 <
b10000 "
b10000 4
b0 #
b0 3
b1 )
b1 ,
1(
#2600
0(
#2620
b10 7
b10010 6
b10 5
b10100101 =
b101 ?
b101 ;
b100 :
b1 !
b1 <
b10001 "
b10001 4
b1 #
b1 3
b10 )
b10 ,
1(
#2640
0(
#2660
b11 7
b10011 6
b11 5
b11100111 =
b111 ?
b111 ;
b110 :
b10 !
b10 <
b10010 "
b10010 4
b10 #
b10 3
b11 )
b11 ,
1(
#2680
0(
#2700
b100 7
b10100 6
b100 5
b100101001 =
b1001 ?
b1001 ;
b1000 :
b11 !
b11 <
b10011 "
b10011 4
b11 #
b11 3
b100 )
b100 ,
1(
#2720
0(
#2740
b101 7
b10101 6
b101 5
b101101011 =
b1011 ?
b1011 ;
b1010 :
b100 !
b100 <
b10100 "
b10100 4
b100 #
b100 3
b101 )
b101 ,
1(
#2760
0(
#2780
b110 7
b10110 6
b110 5
b110101101 =
b1101 ?
b1101 ;
b1100 :
b101 !
b101 <
b10101 "
b10101 4
b101 #
b101 3
b110 )
b110 ,
1(
#2800
0(
#2820
b111 7
b10111 6
b111 5
b111101111 =
b1111 ?
b1111 ;
b1110 :
b110 !
b110 <
b10110 "
b10110 4
b110 #
b110 3
b111 )
b111 ,
1(
#2840
0(
#2860
b1000 7
b11000 6
b1000 5
b1000110001 =
b10001 ?
b10001 ;
b10000 :
b111 !
b111 <
b10111 "
b10111 4
b111 #
b111 3
b1000 )
b1000 ,
1(
#2880
0(
#2900
b1001 7
b11001 6
b1001 5
b1001110011 =
b10011 ?
b10011 ;
b10010 :
b1000 !
b1000 <
b11000 "
b11000 4
b1000 #
b1000 3
b1001 )
b1001 ,
1(
#2920
0(
#2940
b1010 7
b11010 6
b1010 5
b1010110101 =
b10101 ?
b10101 ;
b10100 :
b1001 !
b1001 <
b11001 "
b11001 4
b1001 #
b1001 3
b1010 )
b1010 ,
1(
#2960
0(
#2980
b1011 7
b11011 6
b1011 5
b1011110111 =
b10111 ?
b10111 ;
b10110 :
b1010 !
b1010 <
b11010 "
b11010 4
b1010 #
b1010 3
b1011 )
b1011 ,
1(
#3000
0(
#3020
b1100 7
b11100 6
b1100 5
b1100111001 =
b11001 ?
b11001 ;
b11000 :
b1011 !
b1011 <
b11011 "
b11011 4
b1011 #
b1011 3
b1100 )
b1100 ,
1(
#3040
0(
#3060
b1101 7
b11101 6
b1101 5
b1101111011 =
b11011 ?
b11011 ;
b11010 :
b1100 !
b1100 <
b11100 "
b11100 4
b1100 #
b1100 3
b1101 )
b1101 ,
1(
#3080
0(
#3100
b1110 7
b11110 6
b1110 5
b1110111101 =
b11101 ?
b11101 ;
b11100 :
b1101 !
b1101 <
b11101 "
b11101 4
b1101 #
b1101 3
b1110 )
b1110 ,
1(
#3120
0(
#3140
b1111 7
b11111 6
b1111 5
b1111111111 =
b11111 ?
b11111 ;
b11110 :
b1110 !
b1110 <
b11110 "
b11110 4
b1110 #
b1110 3
b1111 )
b1111 ,
1(
#3160
0(
#3180
b0 7
b10000 6
b0 5
b100001 =
b1 ?
b1 ;
b0 :
b1111 !
b1111 <
b11111 "
b11111 4
b1111 #
b1111 3
b0 )
b0 ,
1(
